{"fen": "r4k2/1p2qppp/pQp5/4p3/P3P3/2P5/1P3PPP/3R2K1", "white_turn": true, "camera": {"angle": 59, "location": [-0.0300209391862154, -0.20395508408546448, 0.339438259601593]}, "lighting": {"mode": "flash", "flash": {"active": true}, "spot1": {"active": false, "xy_angle": 152, "focus": [-0.15702971816062927, -0.08357954770326614, 0.0], "location": [-0.3178611397743225, 0.1690097600221634, 0.3532830774784088]}, "spot2": {"active": false, "xy_angle": 36, "focus": [-0.07955099642276764, -0.20485647022724152, 0.0], "location": [0.29124611616134644, 0.21160268783569336, 0.3519715964794159]}}, "corners": [[296, 740], [320, 212], [799, 162], [983, 634]], "pieces": [{"piece": "k", "square": "f8", "box": [645, 107, 46, 108]}, {"piece": "r", "square": "a8", "box": [304, 163, 58, 79]}, {"piece": "p", "square": "h7", "box": [772, 192, 32, 49]}, {"piece": "p", "square": "g7", "box": [717, 190, 31, 49]}, {"piece": "p", "square": "f7", "box": [651, 201, 31, 49]}, {"piece": "q", "square": "e7", "box": [588, 168, 45, 101]}, {"piece": "p", "square": "b7", "box": [409, 232, 33, 49]}, {"piece": "p", "square": "c6", "box": [478, 278, 33, 49]}, {"piece": "Q", "square": "b6", "box": [386, 245, 60, 99]}, {"piece": "p", "square": "a6", "box": [337, 295, 38, 49]}, {"piece": "p", "square": "e5", "box": [620, 320, 34, 49]}, {"piece": "P", "square": "e4", "box": [619, 379, 35, 49]}, {"piece": "P", "square": "a4", "box": [326, 424, 42, 48]}, {"piece": "P", "square": "c3", "box": [487, 471, 38, 48]}, {"piece": "P", "square": "h2", "box": [878, 506, 47, 48]}, {"piece": "P", "square": "g2", "box": [800, 504, 42, 48]}, {"piece": "P", "square": "f2", "box": [730, 507, 40, 47]}, {"piece": "P", "square": "b2", "box": [413, 557, 41, 47]}, {"piece": "K", "square": "g1", "box": [828, 548, 93, 91]}, {"piece": "R", "square": "d1", "box": [568, 590, 54, 76]}]}