{"fen": "8/6pp/p4k2/2p5/P1p1R1P1/2P4P/r5P1/5K2", "white_turn": true, "camera": {"angle": 47, "location": [-0.003737605642527342, -0.2700713574886322, 0.28961607813835144]}, "lighting": {"mode": "spotlights", "flash": {"active": false}, "spot1": {"active": true, "xy_angle": 345, "focus": [-0.10786163061857224, 0.08090474456548691, 0.0], "location": [0.3477332890033722, -0.09317485988140106, 0.35132846236228943]}, "spot2": {"active": true, "xy_angle": 151, "focus": [0.2723602056503296, 0.02411089837551117, 0.0], "location": [-0.31486308574676514, 0.1745314598083496, 0.1962861716747284]}}, "corners": [[225, 669], [366, 221], [826, 217], [982, 659]], "pieces": [{"piece": "p", "square": "h7", "box": [798, 231, 32, 50]}, {"piece": "p", "square": "g7", "box": [742, 234, 31, 51]}, {"piece": "k", "square": "f6", "box": [672, 222, 52, 116]}, {"piece": "p", "square": "a6", "box": [347, 279, 34, 52]}, {"piece": "p", "square": "c5", "box": [489, 320, 34, 54]}, {"piece": "P", "square": "g4", "box": [774, 364, 37, 55]}, {"piece": "R", "square": "e4", "box": [615, 346, 47, 90]}, {"piece": "p", "square": "c4", "box": [468, 384, 37, 56]}, {"piece": "P", "square": "a4", "box": [306, 373, 40, 56]}, {"piece": "P", "square": "h3", "box": [846, 432, 43, 57]}, {"piece": "P", "square": "c3", "box": [466, 432, 39, 57]}, {"piece": "P", "square": "g2", "box": [787, 492, 43, 59]}, {"piece": "r", "square": "a2", "box": [270, 473, 78, 97]}, {"piece": "K", "square": "f1", "box": [726, 515, 80, 123]}]}