{"fen": "r3rbk1/1bpq1ppp/p1np1n2/1p2p3/4P3/PBPP1N1P/1P1N1PP1/R1BQR1K1", "white_turn": true, "camera": {"angle": 56, "location": [0.05433619022369385, -0.221440389752388, 0.3282988667488098]}, "lighting": {"mode": "flash", "flash": {"active": true}, "spot1": {"active": false, "xy_angle": 112, "focus": [0.08445005118846893, 0.07239406555891037, 0.0], "location": [-0.1348583698272705, 0.3337861895561218, 0.25836649537086487]}, "spot2": {"active": false, "xy_angle": 233, "focus": [-0.38852348923683167, -0.3013851046562195, 0.0], "location": [-0.21665340662002563, -0.2875087857246399, 0.25083431601524353]}}, "corners": [[198, 590], [433, 163], [899, 241], [875, 762]], "pieces": [{"piece": "k", "square": "g8", "box": [781, 155, 61, 109]}, {"piece": "b", "square": "f8", "box": [712, 159, 44, 90]}, {"piece": "r", "square": "e8", "box": [661, 161, 41, 78]}, {"piece": "r", "square": "a8", "box": [432, 121, 44, 77]}, {"piece": "p", "square": "h7", "box": [853, 267, 37, 50]}, {"piece": "p", "square": "g7", "box": [776, 247, 33, 50]}, {"piece": "p", "square": "f7", "box": [701, 249, 32, 50]}, {"piece": "q", "square": "d7", "box": [580, 176, 44, 102]}, {"piece": "p", "square": "c7", "box": [517, 213, 30, 49]}, {"piece": "b", "square": "b7", "box": [468, 158, 42, 90]}, {"piece": "n", "square": "f6", "box": [707, 258, 38, 82]}, {"piece": "p", "square": "d6", "box": [565, 270, 32, 50]}, {"piece": "n", "square": "c6", "box": [518, 228, 37, 72]}, {"piece": "p", "square": "a6", "box": [400, 228, 32, 49]}, {"piece": "p", "square": "e5", "box": [619, 326, 33, 50]}, {"piece": "p", "square": "b5", "box": [433, 284, 33, 50]}, {"piece": "P", "square": "e4", "box": [614, 390, 35, 50]}, {"piece": "P", "square": "h3", "box": [829, 520, 45, 51]}, {"piece": "N", "square": "f3", "box": [681, 458, 43, 74]}, {"piece": "P", "square": "d3", "box": [533, 438, 37, 51]}, {"piece": "P", "square": "c3", "box": [437, 432, 38, 51]}, {"piece": "B", "square": "b3", "box": [358, 373, 61, 89]}, {"piece": "P", "square": "a3", "box": [294, 381, 42, 51]}, {"piece": "P", "square": "g2", "box": [735, 571, 42, 50]}, {"piece": "P", "square": "f2", "box": [661, 538, 40, 51]}, {"piece": "N", "square": "d2", "box": [488, 494, 52, 78]}, {"piece": "P", "square": "b2", "box": [343, 470, 42, 51]}, {"piece": "K", "square": "g1", "box": [713, 614, 80, 97]}, {"piece": "R", "square": "e1", "box": [545, 582, 54, 82]}, {"piece": "Q", "square": "d1", "box": [456, 573, 65, 93]}, {"piece": "B", "square": "c1", "box": [359, 539, 68, 83]}, {"piece": "R", "square": "a1", "box": [182, 497, 86, 83]}]}