{"fen": "1b2rqk1/1R3p1p/5Qp1/8/2N2p1P/2P5/1P3PK1/8", "white_turn": true, "camera": {"angle": 56, "location": [0.04993313550949097, -0.221440389752388, 0.3282988667488098]}, "lighting": {"mode": "spotlights", "flash": {"active": false}, "spot1": {"active": true, "xy_angle": 115, "focus": [0.1626397967338562, -0.2951571047306061, 0.0], "location": [-0.15214256942272186, 0.32627078890800476, 0.3224567472934723]}, "spot2": {"active": true, "xy_angle": 157, "focus": [0.2876584827899933, -0.2977432608604431, 0.0], "location": [-0.33138173818588257, 0.14066320657730103, 0.25573214888572693]}}, "corners": [[200, 598], [427, 165], [895, 236], [882, 757]], "pieces": [{"piece": "k", "square": "g8", "box": [779, 156, 61, 108]}, {"piece": "q", "square": "f8", "box": [722, 144, 49, 102]}, {"piece": "r", "square": "e8", "box": [653, 157, 41, 78]}, {"piece": "b", "square": "b8", "box": [494, 119, 39, 90]}, {"piece": "p", "square": "h7", "box": [844, 267, 37, 50]}, {"piece": "p", "square": "f7", "box": [718, 233, 32, 49]}, {"piece": "R", "square": "b7", "box": [455, 178, 45, 79]}, {"piece": "p", "square": "g6", "box": [776, 303, 34, 50]}, {"piece": "Q", "square": "f6", "box": [701, 242, 52, 102]}, {"piece": "P", "square": "h4", "box": [827, 433, 42, 51]}, {"piece": "p", "square": "f4", "box": [681, 403, 36, 51]}, {"piece": "N", "square": "c4", "box": [468, 340, 44, 79]}, {"piece": "P", "square": "c3", "box": [440, 428, 38, 51]}, {"piece": "K", "square": "g2", "box": [738, 525, 79, 100]}, {"piece": "P", "square": "f2", "box": [664, 543, 40, 50]}, {"piece": "P", "square": "b2", "box": [345, 472, 42, 51]}]}